{"expireTime":9007200917220393000,"key":"779c2edd8cc459e82e89123c853376e0","val":{"name":"IMAGE_PROCESSING","inputPaths":["/home/venom/Desktop/sdakgs/chinalantern.github.io/content/featured/HalcyonTheme/today_ai.png"],"outputDir":"/home/venom/Desktop/sdakgs/chinalantern.github.io/public/static/3b80c275fa369c43e8bb2a3bdaefe4c7","args":{"isLazy":false,"operations":[{"outputPath":"a8dfe/today_ai.png","args":{"height":99,"width":175,"cropFocus":17,"toFormat":"png","fit":"cover"}},{"outputPath":"aef44/today_ai.png","args":{"height":199,"width":350,"cropFocus":17,"toFormat":"png","fit":"cover"}},{"outputPath":"66323/today_ai.png","args":{"height":397,"width":700,"cropFocus":17,"toFormat":"png","fit":"cover"}},{"outputPath":"3473c/today_ai.png","args":{"height":794,"width":1400,"cropFocus":17,"toFormat":"png","fit":"cover"}}],"pluginOptions":{"base64Width":20,"forceBase64Format":"","useMozJpeg":false,"stripMetadata":true,"lazyImageGeneration":true,"defaultQuality":50,"failOnError":true,"plugins":[]}}}}